config_manager.py
host_selector.py
save_config.py
ssh_dir_browser.py
ssh_handler.py
vscode_integration.py
ssh_to_code-1.0.0.dist-info/licenses/LICENSE
ssh_to_code-1.0.0.dist-info/METADATA
ssh_to_code-1.0.0.dist-info/WHEEL
ssh_to_code-1.0.0.dist-info/entry_points.txt
ssh_to_code-1.0.0.dist-info/top_level.txt
ssh_to_code-1.0.0.dist-info/RECORD
