Metadata-Version: 2.4
Name: ssh-to-code
Version: 1.0.0
Summary: Terminal-based SSH directory browser with VS Code integration
Author-email: Rajesh <rajesh-cs18@users.noreply.github.com>
License-Expression: MIT
Project-URL: Homepage, https://github.com/rajesh-cs18/ssh-to-code
Project-URL: Bug Tracker, https://github.com/rajesh-cs18/ssh-to-code/issues
Project-URL: Repository, https://github.com/rajesh-cs18/ssh-to-code
Project-URL: Documentation, https://github.com/rajesh-cs18/ssh-to-code#readme
Keywords: ssh,vscode,terminal,directory-browser,remote-development
Classifier: Development Status :: 4 - Beta
Classifier: Environment :: Console
Classifier: Environment :: Console :: Curses
Classifier: Intended Audience :: Developers
Classifier: Intended Audience :: System Administrators
Classifier: Operating System :: POSIX :: Linux
Classifier: Operating System :: MacOS
Classifier: Programming Language :: Python :: 3
Classifier: Programming Language :: Python :: 3.7
Classifier: Programming Language :: Python :: 3.8
Classifier: Programming Language :: Python :: 3.9
Classifier: Programming Language :: Python :: 3.10
Classifier: Programming Language :: Python :: 3.11
Classifier: Programming Language :: Python :: 3.12
Classifier: Topic :: System :: Systems Administration
Classifier: Topic :: Utilities
Requires-Python: >=3.7
License-File: LICENSE
Requires-Dist: paramiko>=3.0.0
Dynamic: license-file
